aws_s3_access_grants_boto3_plugin/__init__.py
aws_s3_access_grants_boto3_plugin/exceptions.py
aws_s3_access_grants_boto3_plugin/operation_permissions.py
aws_s3_access_grants_boto3_plugin/s3_access_grants_plugin.py
aws_s3_access_grants_boto3_plugin/cache/__init__.py
aws_s3_access_grants_boto3_plugin/cache/access_denied_cache.py
aws_s3_access_grants_boto3_plugin/cache/access_grants_cache.py
aws_s3_access_grants_boto3_plugin/cache/account_id_resolver_cache.py
aws_s3_access_grants_boto3_plugin/cache/bucket_region_resolver_cache.py
aws_s3_access_grants_boto3_plugin/cache/cache_key.py
aws_s3_access_grants_boto3_plugin-1.3.0.dist-info/METADATA
aws_s3_access_grants_boto3_plugin-1.3.0.dist-info/WHEEL
aws_s3_access_grants_boto3_plugin-1.3.0.dist-info/licenses/LICENSE
aws_s3_access_grants_boto3_plugin-1.3.0.dist-info/licenses/NOTICE
aws_s3_access_grants_boto3_plugin-1.3.0.dist-info/RECORD
