Metadata-Version: 2.4
Name: aws_s3_access_grants_boto3_plugin
Version: 1.3.0
Summary: AWS S3 Access Grants plugin provides the functionality to enable S3 customers to configure S3 Access Grants as a permission layer on top of the S3 Clients.
Project-URL: Homepage, https://github.com/aws/boto3-s3-access-grants-plugin
Project-URL: Issues, https://github.com/aws/boto3-s3-access-grants-plugin/issues
License-File: LICENSE
License-File: NOTICE
Classifier: Operating System :: OS Independent
Classifier: Programming Language :: Python :: 3
Requires-Python: >=3.9
Requires-Dist: botocore>=1.39.9
Requires-Dist: cacheout>=0.16.0
